shadowdragon/__init__.py
shadowdragon/shadowdragon.py
shadowdragon-0.0.7.dist-info/LICENSE
shadowdragon-0.0.7.dist-info/METADATA
shadowdragon-0.0.7.dist-info/WHEEL
shadowdragon-0.0.7.dist-info/top_level.txt
shadowdragon-0.0.7.dist-info/RECORD
