Metadata-Version: 2.1
Name: shadowdragon
Version: 0.0.7
Summary: An async wrapper for the ShadowDragon API
Author-email: Kojin Glick <kglick@middlebury.edu>
Project-URL: Homepage, https://github.com/kojinglick-ctec/shadowdragon/
Project-URL: Issues, https://github.com/kojinglick-ctec/shadowdragon/issues
Classifier: Programming Language :: Python :: 3
Classifier: License :: OSI Approved :: MIT License
Classifier: Operating System :: OS Independent
Requires-Python: >=3.8
License-File: LICENSE
Requires-Dist: aiohttp
